wexample_prompt-0.0.97.dist-info/METADATA
wexample_prompt-0.0.97.dist-info/WHEEL
wexample_prompt-0.0.97.dist-info/entry_points.txt
wexample_prompt/__init__.py
wexample_prompt/__pycache__/__init__.py
wexample_prompt/common/__init__.py
wexample_prompt/common/__pycache__/__init__.py
wexample_prompt/common/choice/__init__.py
wexample_prompt/common/choice/choice.py
wexample_prompt/common/color_manager.py
wexample_prompt/common/io_manager.py
wexample_prompt/common/progress/__init__.py
wexample_prompt/common/progress/__pycache__/__init__.py
wexample_prompt/common/progress/progress_handle.py
wexample_prompt/common/progress/range_progress_handle.py
wexample_prompt/common/prompt_context.py
wexample_prompt/common/prompt_response_line.py
wexample_prompt/common/prompt_response_segment.py
wexample_prompt/common/spinner_pool.py
wexample_prompt/common/style_markup_parser.py
wexample_prompt/const/__init__.py
wexample_prompt/const/__pycache__/__init__.py
wexample_prompt/const/spinners.py
wexample_prompt/const/types.py
wexample_prompt/enums/__init__.py
wexample_prompt/enums/__pycache__/__init__.py
wexample_prompt/enums/choice.py
wexample_prompt/enums/indentation_style.py
wexample_prompt/enums/response_type.py
wexample_prompt/enums/terminal_bg_color.py
wexample_prompt/enums/terminal_color.py
wexample_prompt/enums/text_style.py
wexample_prompt/enums/verbosity_level.py
wexample_prompt/example/__init__.py
wexample_prompt/example/abstract_response_example.py
wexample_prompt/example/example_class_with_methods.py
wexample_prompt/example/helpers/__init__.py
wexample_prompt/example/helpers/nesting_demo_classes.py
wexample_prompt/example/helpers/output_message_mixin.py
wexample_prompt/example/interactive_example.py
wexample_prompt/example/interactive_executor.py
wexample_prompt/example/response/__init__.py
wexample_prompt/example/response/abstract_simple_message_example.py
wexample_prompt/example/response/abstract_title_example.py
wexample_prompt/example/response/data/__init__.py
wexample_prompt/example/response/data/list_example.py
wexample_prompt/example/response/data/multiple_example.py
wexample_prompt-0.0.97.dist-info/RECORD
